{
	"absolute": {
		"style": {
			"position": "absolute"
		}
	},
	"my-5": {
		"style": {
			"marginTop": 20,
			"marginBottom": 20
		}
	},
	"mx-10": {
		"style": {
			"marginLeft": 40,
			"marginRight": 40
		}
	},
	"mt-36": {
		"style": {
			"marginTop": 144
		}
	},
	"mt-5": {
		"style": {
			"marginTop": 20
		}
	},
	"mt-20": {
		"style": {
			"marginTop": 80
		}
	},
	"flex": {
		"style": {
			"display": "flex"
		}
	},
	"h-full": {
		"style": {
			"height": "100%"
		}
	},
	"justify-center": {
		"style": {
			"justifyContent": "center"
		}
	},
	"self-center": {
		"style": {
			"alignSelf": "center"
		}
	},
	"rounded": {
		"style": {
			"borderTopLeftRadius": 4,
			"borderTopRightRadius": 4,
			"borderBottomRightRadius": 4,
			"borderBottomLeftRadius": 4
		}
	},
	"bg-white": {
		"style": {
			"--tw-bg-opacity": 1,
			"backgroundColor": "rgb(255 255 255 / var(--tw-bg-opacity))"
		}
	},
	"font-bold": {
		"style": {
			"fontWeight": "700"
		}
	},
	"text-black": {
		"style": {
			"--tw-text-opacity": 1,
			"color": "rgb(0 0 0 / var(--tw-text-opacity))"
		}
	},
	"text-blue-500": {
		"style": {
			"--tw-text-opacity": 1,
			"color": "rgb(59 130 246 / var(--tw-text-opacity))"
		}
	}
}